<AutecologyXML xmlns="https://github.com/Deltares/KnowledgeRules" xmlns:xsi="http://www.w3.org/2001/XMLSchema-instance" xsi:schemaLocation="https://github.com/Deltares/KnowledgeRules ../../../xmlschema/AutecologyXML.xsd">
	<Topic>
		<Species>
			<EoLpagenr>45509333</EoLpagenr>
			<LatName>Chlidonias niger</LatName>
			<CommonNames>
				<Name name="Zwarte stern" language="NL"/>
			</CommonNames>
			<SpecCode/>
		</Species>
	</Topic>
	<Autecology>
		<ModelType name="HSI">
			<System name="adult">
				<Scope>
					<SpatialScope>
						<GeoNames name="Netherlands" id="2750405"/>
					</SpatialScope>
					<TemporalScope>
						<StartDate>1979-01-01</StartDate>
						<EndDate>1994-01-01</EndDate>
					</TemporalScope>
				</Scope>
				<SystemDescription>
					<Description language="NL">
						<text>&lt;p&gt;Het nest wordt gemaakt op het wateroppervlak en aan de waterkant.&lt;/p&gt;

&lt;p&gt;Het voedsel wordt gezocht op de onder water, aan het wateroppervlak, aan de waterkant, in de kruilaag en in de stuiklaag.&lt;/p&gt;

&lt;p&gt;De bepalende factor van voorkomen is de aanwezigheid van ondiep open water, eilandjes en/of drijvende waterplanten en grote insecten, .&lt;/p&gt;



&lt;h1 id="Zwartestern-Chlidoniasniger-Onzekerheidenvalidatie"&gt;Onzekerheid en validatie&lt;/h1&gt;

&lt;p&gt;&lt;img class="emoticon emoticon-warning" src="./Zwarte stern - Chlidonias niger - HABITAT - Spatial analysis tool - Deltares Public Wiki_files/warning.svg" data-emoticon-name="warning" alt="(warning)"&gt; Deze rekenregels zijn niet gevalideerd.&lt;/p&gt;

&lt;p&gt;Deze rekenregels zijn opgesteld aan de hand van een literatuuronderzoek &lt;a href="https://publicwiki.deltares.nl/display/HBTHOME/Zwarte+stern+-+Chlidonias+niger#Zwartestern-Chlidoniasniger-1"&gt;#1&lt;/a&gt;.&lt;/p&gt;

&lt;h1 id="Zwartestern-Chlidoniasniger-Toepassingsgebied"&gt;Toepassingsgebied&lt;/h1&gt;

&lt;p&gt;Deze rekenregels zijn opgesteld voor de zwarte nabij Rijkswateren &lt;a href="https://publicwiki.deltares.nl/display/HBTHOME/Zwarte+stern+-+Chlidonias+niger#Zwartestern-Chlidoniasniger-1"&gt;#1&lt;/a&gt;. &lt;/p&gt;

&lt;h1 id="Zwartestern-Chlidoniasniger-Voorbeeldproject"&gt;Voorbeeld project&lt;/h1&gt;

&lt;p&gt;Niet aanwezig&lt;/p&gt;</text>
					</Description>
				</SystemDescription>
				<SystemFlowDiagrams>
					<FlowDiagram name="breeding_area">
						<From name="breeding_area">
							<label>"breeding_area"</label>
							<equation>min</equation>
							<To>nesting_area</To>
							<To>feeding_area</To>
							<To>breeding_area_general</To>
						</From>
						<From name="nesting_area">
							<label>"nesting_area"</label>
							<equation>min</equation>
							<To>location</To>
							<To>daily_waterlevel_fluctuation</To>
							<To>flooding_period</To>
						</From>
						<From name="feeding_area">
							<label>"feeding_area"</label>
							<equation>average</equation>
							<To>surfacewater_area</To>
							<To>meadow_distance</To>
						</From>
						<From name="breeding_area_general">
							<label>"breeding_area_general"</label>
							<equation>average</equation>
							<To>surfacewater_width</To>
							<To>enclosure_landscape</To>
							<To>area_of_marshland</To>
						</From>
						<From name="location">
							<label>"location"</label>
							<equation>average</equation>
							<To>nesting_location</To>
							<To>locations_with_emers_plants</To>
						</From>
						<From name="nesting_location">
							<label>"nesting_location"</label>
							<equation>min</equation>
							<To>nesting_places</To>
							<To>height_above_watersurface</To>
						</From>
					</FlowDiagram>
				</SystemFlowDiagrams>
				<KnowledgeRules>
					<ResponseCurve name="surfacewater_area">
						<inputLayers>
							<layer name="surfacewater_area">
								<parameter_cat>TOBEFILLED</parameter_cat>
								<layer_filename>surfacewater_area</layer_filename>
								<unit>"%"</unit>
								<statistic>average</statistic>
								<description>TOBEFILLED</description>
							</layer>
						</inputLayers>
						<Content>
							<type>scalar</type>
							<description>"Amount of surface water within 3 kilometers in percent"</description>
							<author>"Marc Weeber"</author>
							<date>2013-01-15</date>
							<references>
								<reference author="Van der Winden, J., Dirksen, S., Poot, M.J.M." year="1996" title="" journal="" identification=""/>
							</references>
							<valuesScalar>
								<parameter input="0" output="0.0"/>
								<parameter input="5" output="0.7"/>
								<parameter input="25" output="1.0"/>
								<parameter input="50" output="1.0"/>
								<parameter input="100" output="0.0"/>
							</valuesScalar>
						</Content>
						<outputLayers>
							<layer name="HSI_surfacewater_area">
								<parameter_cat>HSI</parameter_cat>
								<layer_filename>HSI_surfacewater_area</layer_filename>
								<unit>factor</unit>
								<statistic>average</statistic>
								<description>TOBEFILLED</description>
							</layer>
						</outputLayers>
					</ResponseCurve>
					<ResponseCurve name="surfacewater_width">
						<inputLayers>
							<layer name="surfacewater_width">
								<parameter_cat>TOBEFILLED</parameter_cat>
								<layer_filename>surfacewater_width</layer_filename>
								<unit>"m"</unit>
								<statistic>average</statistic>
								<description>TOBEFILLED</description>
							</layer>
						</inputLayers>
						<Content>
							<type>scalar</type>
							<description>"Width of surface water in meters"</description>
							<author>"Marc Weeber"</author>
							<date>2013-01-15</date>
							<references>
								<reference author="Van der Winden, J., Dirksen, S., Poot, M.J.M." year="1996" title="" journal="" identification=""/>
							</references>
							<valuesScalar>
								<parameter input="1" output="0.8"/>
								<parameter input="25" output="1.0"/>
								<parameter input="100" output="0.4"/>
								<parameter input="200" output="0.0"/>
								<parameter input="250" output="0.0"/>
							</valuesScalar>
						</Content>
						<outputLayers>
							<layer name="HSI_surfacewater_width">
								<parameter_cat>HSI</parameter_cat>
								<layer_filename>HSI_surfacewater_width</layer_filename>
								<unit>factor</unit>
								<statistic>average</statistic>
								<description>TOBEFILLED</description>
							</layer>
						</outputLayers>
					</ResponseCurve>
					<ResponseCurve name="nesting_places">
						<inputLayers>
							<layer name="nesting_places">
								<parameter_cat>TOBEFILLED</parameter_cat>
								<layer_filename>nesting_places</layer_filename>
								<unit>"categorical"</unit>
								<statistic>average</statistic>
								<description>TOBEFILLED</description>
							</layer>
						</inputLayers>
						<Content>
							<type>categorical</type>
							<description>"Types of nesting places"</description>
							<author>"Marc Weeber"</author>
							<date>2013-01-15</date>
							<references>
								<reference author="Van der Winden, J., Dirksen, S., Poot, M.J.M." year="1996" title="" journal="" identification=""/>
							</references>
							<valuesCategorical>
								<parameter input="1" input_cat="bank" output="0.3" output_cat=""/>
								<parameter input="2" input_cat="(wire) algae" output="0.5" output_cat=""/>
								<parameter input="3" input_cat="vegetation patches in water" output="1.0" output_cat=""/>
								<parameter input="4" input_cat="mudbanks" output="0.8" output_cat=""/>
								<parameter input="5" input_cat="floating rhizomes" output="0.8" output_cat=""/>
								<parameter input="6" input_cat="krabbescheer" output="1.0" output_cat=""/>
								<parameter input="7" input_cat="rafts" output="1.0" output_cat=""/>
							</valuesCategorical>
						</Content>
						<outputLayers>
							<layer name="HSI_nesting_places">
								<parameter_cat>HSI</parameter_cat>
								<layer_filename>HSI_nesting_places</layer_filename>
								<unit>factor</unit>
								<statistic>average</statistic>
								<description>TOBEFILLED</description>
							</layer>
						</outputLayers>
					</ResponseCurve>
					<ResponseCurve name="height_above_watersurface">
						<inputLayers>
							<layer name="height_above_watersurface">
								<parameter_cat>TOBEFILLED</parameter_cat>
								<layer_filename>height_above_watersurface</layer_filename>
								<unit>cm</unit>
								<statistic>average</statistic>
								<description>TOBEFILLED</description>
							</layer>
						</inputLayers>
						<Content>
							<type>range / categorical</type>
							<description>Heigth of rafts above the watersurface</description>
							<author>"Marc Weeber"</author>
							<date>2013-01-15</date>
							<references>
								<reference author="Van der Winden, J., Dirksen, S., Poot, M.J.M." year="1996" title="" journal="" identification=""/>
							</references>
							<valuesRangeCategorical>
								<parameter rangemin_input="0" rangemax_input="2" input_cat="0 - 2" output="1.0" output_cat=""/>
								<parameter rangemin_input="2" rangemax_input="3" input_cat="2 - 3" output="0.7" output_cat=""/>
								<parameter rangemin_input="3" rangemax_input="999999" input_cat="&gt; 3" output="0.1" output_cat=""/>
							</valuesRangeCategorical>
						</Content>
						<outputLayers>
							<layer name="HSI_height_above_watersurface">
								<parameter_cat>HSI</parameter_cat>
								<layer_filename>HSI_height_above_watersurface</layer_filename>
								<unit>factor</unit>
								<statistic>average</statistic>
								<description>TOBEFILLED</description>
							</layer>
						</outputLayers>
					</ResponseCurve>
					<ResponseCurve name="daily_waterlevel_fluctuation">
						<inputLayers>
							<layer name="daily_waterlevel_fluctuation">
								<parameter_cat>TOBEFILLED</parameter_cat>
								<layer_filename>daily_waterlevel_fluctuation</layer_filename>
								<unit>cm/day</unit>
								<statistic>average</statistic>
								<description>TOBEFILLED</description>
							</layer>
						</inputLayers>
						<Content>
							<type>range / categorical</type>
							<description>Daily fluctuation of the waterlevel</description>
							<author>"Marc Weeber"</author>
							<date>2013-01-15</date>
							<references>
								<reference author="Van der Winden, J., Dirksen, S., Poot, M.J.M." year="1996" title="" journal="" identification=""/>
							</references>
							<valuesRangeCategorical>
								<parameter rangemin_input="2" rangemax_input="3" input_cat="2 - 3" output="0.7" output_cat=""/>
								<parameter rangemin_input="3" rangemax_input="999999" input_cat="&gt; 3" output="0.1" output_cat=""/>
							</valuesRangeCategorical>
						</Content>
						<outputLayers>
							<layer name="HSI_daily_waterlevel_fluctuation">
								<parameter_cat>HSI</parameter_cat>
								<layer_filename>HSI_daily_waterlevel_fluctuation</layer_filename>
								<unit>factor</unit>
								<statistic>average</statistic>
								<description>TOBEFILLED</description>
							</layer>
						</outputLayers>
					</ResponseCurve>
					<ResponseCurve name="flooding_period">
						<inputLayers>
							<layer name="flooding_period">
								<parameter_cat>TOBEFILLED</parameter_cat>
								<layer_filename>flooding_period</layer_filename>
								<unit>month / category"</unit>
								<statistic>average</statistic>
								<description>TOBEFILLED</description>
							</layer>
						</inputLayers>
						<Content>
							<type>range / categorical</type>
							<description>"Period of flooding"</description>
							<author>"Marc Weeber"</author>
							<date>2013-01-15</date>
							<references>
								<reference author="Van der Winden, J., Dirksen, S., Poot, M.J.M." year="1996" title="" journal="" identification=""/>
							</references>
							<valuesRangeCategorical>
								<parameter rangemin_input="0" rangemax_input="0" input_cat="None" output="1.0" output_cat=""/>
								<parameter rangemin_input="0" rangemax_input="4" input_cat="till April" output="1.0" output_cat=""/>
								<parameter rangemin_input="5" rangemax_input="6" input_cat="till June" output="0.6" output_cat=""/>
								<parameter rangemin_input="7" rangemax_input="7" input_cat="till Juli" output="0.1" output_cat=""/>
							</valuesRangeCategorical>
						</Content>
						<outputLayers>
							<layer name="HSI_flooding_period">
								<parameter_cat>HSI</parameter_cat>
								<layer_filename>HSI_flooding_period</layer_filename>
								<unit>factor</unit>
								<statistic>average</statistic>
								<description>TOBEFILLED</description>
							</layer>
						</outputLayers>
					</ResponseCurve>
					<ResponseCurve name="locations_with_emers_plants">
						<inputLayers>
							<layer name="locations_with_emers_plants">
								<parameter_cat>TOBEFILLED</parameter_cat>
								<layer_filename>locations_with_emers_plants</layer_filename>
								<unit>"category"</unit>
								<statistic>average</statistic>
								<description>TOBEFILLED</description>
							</layer>
						</inputLayers>
						<Content>
							<type>categorical</type>
							<description>"Presence of locations with a coverage with emerse plants of mere than 50%"</description>
							<author>"Marc Weeber"</author>
							<date>2013-01-15</date>
							<references>
								<reference author="Van der Winden, J., Dirksen, S., Poot, M.J.M." year="1996" title="" journal="" identification=""/>
							</references>
							<valuesCategorical>
								<parameter input="1" input_cat="present" output="1.0" output_cat=""/>
								<parameter input="2" input_cat="absent" output="0.0" output_cat=""/>
							</valuesCategorical>
						</Content>
						<outputLayers>
							<layer name="HSI_locations_with_emers_plants">
								<parameter_cat>HSI</parameter_cat>
								<layer_filename>HSI_locations_with_emers_plants</layer_filename>
								<unit>factor</unit>
								<statistic>average</statistic>
								<description>TOBEFILLED</description>
							</layer>
						</outputLayers>
					</ResponseCurve>
					<ResponseCurve name="enclosure_landscape">
						<inputLayers>
							<layer name="enclosure_landscape">
								<parameter_cat>TOBEFILLED</parameter_cat>
								<layer_filename>enclosure_landscape</layer_filename>
								<unit>"category"</unit>
								<statistic>average</statistic>
								<description>TOBEFILLED</description>
							</layer>
						</inputLayers>
						<Content>
							<type>categorical</type>
							<description>"Enclosure of the landscape (bosopslag)"</description>
							<author>"Marc Weeber"</author>
							<date>2013-01-15</date>
							<references>
								<reference author="Van der Winden, J., Dirksen, S., Poot, M.J.M." year="1996" title="" journal="" identification=""/>
							</references>
							<valuesCategorical>
								<parameter input="1" input_cat="present" output="1.0" output_cat=""/>
								<parameter input="2" input_cat="absent" output="0.0" output_cat=""/>
							</valuesCategorical>
						</Content>
						<outputLayers>
							<layer name="HSI_enclosure_landscape">
								<parameter_cat>HSI</parameter_cat>
								<layer_filename>HSI_enclosure_landscape</layer_filename>
								<unit>factor</unit>
								<statistic>average</statistic>
								<description>TOBEFILLED</description>
							</layer>
						</outputLayers>
					</ResponseCurve>
					<ResponseCurve name="area_of_marshland">
						<inputLayers>
							<layer name="area_of_marshland">
								<parameter_cat>TOBEFILLED</parameter_cat>
								<layer_filename>area_of_marshland</layer_filename>
								<unit>"ha"</unit>
								<statistic>average</statistic>
								<description>TOBEFILLED</description>
							</layer>
						</inputLayers>
						<Content>
							<type>scalar</type>
							<description>"Area of marshland within 3 kilometers in hectares"</description>
							<author>"Marc Weeber"</author>
							<date>2013-01-15</date>
							<references>
								<reference author="Van der Winden, J., Dirksen, S., Poot, M.J.M." year="1996" title="" journal="" identification=""/>
							</references>
							<valuesScalar>
								<parameter input="0" output="0.0"/>
								<parameter input="25" output="0.5"/>
								<parameter input="200" output="1.0"/>
								<parameter input="250" output="1.0"/>
							</valuesScalar>
						</Content>
						<outputLayers>
							<layer name="HSI_area_of_marshland">
								<parameter_cat>HSI</parameter_cat>
								<layer_filename>HSI_area_of_marshland</layer_filename>
								<unit>factor</unit>
								<statistic>average</statistic>
								<description>TOBEFILLED</description>
							</layer>
						</outputLayers>
					</ResponseCurve>
					<ResponseCurve name="meadow_distance">
						<inputLayers>
							<layer name="meadow_distance">
								<parameter_cat>TOBEFILLED</parameter_cat>
								<layer_filename>meadow_distance</layer_filename>
								<unit>"category"</unit>
								<statistic>average</statistic>
								<description>TOBEFILLED</description>
							</layer>
						</inputLayers>
						<Content>
							<type>categorical</type>
							<description>"Presence of meadows within 3 kilometers"</description>
							<author>"Marc Weeber"</author>
							<date>2013-01-15</date>
							<references>
								<reference author="Van der Winden, J., Dirksen, S., Poot, M.J.M." year="1996" title="" journal="" identification=""/>
							</references>
							<valuesCategorical>
								<parameter input="1" input_cat="present" output="0.0" output_cat=""/>
								<parameter input="2" input_cat="absent" output="0.8" output_cat=""/>
							</valuesCategorical>
						</Content>
						<outputLayers>
							<layer name="HSI_meadow_distance">
								<parameter_cat>HSI</parameter_cat>
								<layer_filename>HSI_meadow_distance</layer_filename>
								<unit>factor</unit>
								<statistic>average</statistic>
								<description>TOBEFILLED</description>
							</layer>
						</outputLayers>
					</ResponseCurve>
				</KnowledgeRules>
			</System>
		</ModelType>
	</Autecology>
	<TopicDescription>
		<Description language="NL">
			<text>&lt;h3 id="Zwartestern-Chlidoniasniger-Algemeenvoorkomen(Broedhabitat)"&gt;Algemeen voorkomen (Broedhabitat)&lt;/h3&gt;

&lt;p&gt;De zwarte stern is een koloniebroeder en broedt in laagveen moerassen, laagveengraslanden en moerassen in rivierkleigebieden. Kleine aantallen komen nog voor in vennen en hoogvenen. In de Rijkswateren worden de zwarte sterns vooral aangetroffen in de uiterwaarden van de grote rivieren &lt;a href="https://publicwiki.deltares.nl/display/HBTHOME/Zwarte+stern+-+Chlidonias+niger#Zwartestern-Chlidoniasniger-1"&gt;#1&lt;/a&gt;.&lt;/p&gt;

&lt;p&gt;De nesten worden gebouwd daar waar veel drijvende vegetatie te vinden is, zoals middelgrote moerassen, dode rivierarmen, poelen, maar ook in sloten. De zwarte stern maakt vaak zijn nesten op krabbescheer (Straiotes aloides). Echter ook ander drijvend plantenmateriaal wordt geaccepteerd voor de nestbouw, zoals drijvende wortelstokken van waterlelie, gele plomp, lisdodde, algenmatten, lage oevervegetatie of drijvend materiaal als planken en boomstammen. In het rivierengebied wordt er met name gebroed op zogenoemde nestvlotjes. Verder heeft de zwarte stern, omdat hij verstoringsgevoelig is, een voorkeur voor een leefomgeving met hoge bedekking van drijvende watervegetatie &lt;a href="https://publicwiki.deltares.nl/display/HBTHOME/Zwarte+stern+-+Chlidonias+niger#Zwartestern-Chlidoniasniger-1"&gt;#1&lt;/a&gt;.&lt;/p&gt;

&lt;p&gt;Peilfluctuatie moet beperkt zijn om het wegspoelen van nesten te voorkomen, om deze reden moeten overstromingen van nesten tijdens het broedseizoen voorkomen worden &lt;a href="https://publicwiki.deltares.nl/display/HBTHOME/Zwarte+stern+-+Chlidonias+niger#Zwartestern-Chlidoniasniger-1"&gt;#1&lt;/a&gt;.&lt;/p&gt;

&lt;h3 id="Zwartestern-Chlidoniasniger-Voedselhabitatenstrategie"&gt;Voedselhabitat en strategie&lt;/h3&gt;

&lt;p&gt;Over het algemeen foerageert de Zwarte stern bij de broedplaats, maar afstanden tot zo'n 3 km van de broedplaats zijn mogelijk. De zwarte stern prefereert gebieden met veel grote insecten, kleine vis en amfibieën. De mogelijkheid om te kunnen variëren in prooi is van belang &lt;a href="https://publicwiki.deltares.nl/display/HBTHOME/Zwarte+stern+-+Chlidonias+niger#Zwartestern-Chlidoniasniger-1"&gt;#1&lt;/a&gt;.&lt;/p&gt;

&lt;h3 id="Zwartestern-Chlidoniasniger-Reproductieenmigratie"&gt;Reproductie en migratie&lt;/h3&gt;

&lt;p&gt;De kolonies zijn aanwezig van eind april tot eind juli - begin augustus. Het leggen van eieren start in het algemeen vanaf 10 mei en het legsel bestaat uit 3 eieren. Na 19 tot 23 dagen zijn deze uitgebroed en na 16 tot 25 dagen zijn de jongen vliegvlug &lt;a href="https://publicwiki.deltares.nl/display/HBTHOME/Zwarte+stern+-+Chlidonias+niger#Zwartestern-Chlidoniasniger-1"&gt;#1&lt;/a&gt;. &lt;/p&gt;

&lt;p&gt;Vanaf juli trekt de zwarte stern naar de kust van tropisch Afrika. Vanaf eind april komen de vogels terug &lt;a href="https://publicwiki.deltares.nl/display/HBTHOME/Zwarte+stern+-+Chlidonias+niger#Zwartestern-Chlidoniasniger-1"&gt;#1&lt;/a&gt;. &lt;/p&gt;

&lt;h3 id="Zwartestern-Chlidoniasniger-Leeftijdenmortaliteit"&gt;Leeftijd en mortaliteit&lt;/h3&gt;

&lt;p&gt;Bij gevaar verlaten de jongen de nesten. Zij schuilen dan in de nabijgelegen vegetatie. Dag-actieve predatoren maken nauwelijks kans, echter nacht-actieve predatoren kunnen een sterke invloed hebben op het nest succes &lt;a href="https://publicwiki.deltares.nl/display/HBTHOME/Zwarte+stern+-+Chlidonias+niger#Zwartestern-Chlidoniasniger-1"&gt;#1&lt;/a&gt;. &lt;/p&gt;
</text>
		</Description>
	</TopicDescription>
	<Documentation>
		<reference author="Van der Winden, J., Dirksen, S., Poot, M.J.M." year="1996" title="HSI-modellen voor 15 oevergebonden vroedvogelsoorten." journal="Ministerie van verkeer en waterstaat, Dienst weg en waterbouwkunde, Bureau Waardenburg" identification="februari 1996"/>
		<reference author="Sierdsema, H." year="1995" title="Broedvogels en beheer." journal="" identification=""/>
	</Documentation>
	<DataSources/>
</AutecologyXML>
